{
  "version": "1.0",
  "defaultProvider": "cdnjs",
  "libraries": [
    {
      "library": "twitter-bootstrap@5.1.3",
      "destination": "wwwroot/lib/twitter-bootstrap/"
    },
    {
      "library": "jquery@3.6.0",
      "destination": "wwwroot/lib/jquery/"
    },
    {
      "library": "font-awesome@6.1.1",
      "destination": "wwwroot/lib/font-awesome/"
    },
    {
      "library": "admin-lte@3.2.0",
      "destination": "wwwroot/lib/admin-lte/"
    },
    {
      "library": "datatables@1.10.21",
      "destination": "wwwroot/lib/datatables/"
    }
  ]
}